nonebot_plugin_make_choice/__init__.py
nonebot_plugin_make_choice/config.py
nonebot_plugin_make_choice-1.0.6.dist-info/LICENSE
nonebot_plugin_make_choice-1.0.6.dist-info/METADATA
nonebot_plugin_make_choice-1.0.6.dist-info/WHEEL
nonebot_plugin_make_choice-1.0.6.dist-info/RECORD
