Metadata-Version: 2.1
Name: nonebot-plugin-make-choice
Version: 1.0.6
Summary: 选择困难症？Bot帮你选！
License: MIT
Author: SherkeyXD
Author-email: 253294679@qq.com
Requires-Python: >=3.9,<4.0
Classifier: License :: OSI Approved :: MIT License
Classifier: Programming Language :: Python :: 3
Classifier: Programming Language :: Python :: 3.9
Classifier: Programming Language :: Python :: 3.10
Classifier: Programming Language :: Python :: 3.11
Classifier: Programming Language :: Python :: 3.12
Classifier: Programming Language :: Python :: 3.13
Requires-Dist: nonebot-adapter-onebot (>=2.3.1,<3.0.0)
Requires-Dist: nonebot2 (>=2.1.0,<3.0.0)
